setup.cfg
setup.py
stupidlib/__init__.py
stupidlib.egg-info/PKG-INFO
stupidlib.egg-info/SOURCES.txt
stupidlib.egg-info/dependency_links.txt
stupidlib.egg-info/not-zip-safe
stupidlib.egg-info/top_level.txt