Metadata-Version: 2.2
Name: stupidlib
Version: 0.1
Summary: Degrade to the maximum
Author-email: vsevolodrodionov99@gmail.com
Dynamic: author-email
Dynamic: summary
